Digital_India_Act/__init__.py
Digital_India_Act/config.py
Digital_India_Act/Hybrid_based_Features/__init__.py
Digital_India_Act/Hybrid_based_Features/AccessbilityChecker/__init__.py
Digital_India_Act/Hybrid_based_Features/AccessbilityChecker/accessibility_checker.py
Digital_India_Act/Hybrid_based_Features/AccessbilityChecker/groq_client.py
Digital_India_Act/Hybrid_based_Features/AccessbilityChecker/llm_engine.py
Digital_India_Act/Hybrid_based_Features/AccessbilityChecker/models.py
Digital_India_Act/Hybrid_based_Features/AccessbilityChecker/report_writer.py
Digital_India_Act/Hybrid_based_Features/AccessbilityChecker/rule_engine.py
Digital_India_Act/Hybrid_based_Features/ChildSafetyChecker/__init__.py
Digital_India_Act/Hybrid_based_Features/ChildSafetyChecker/evaluator.py
Digital_India_Act/Hybrid_based_Features/ChildSafetyChecker/groq_llm_client.py
Digital_India_Act/Hybrid_based_Features/ChildSafetyChecker/llm_engine.py
Digital_India_Act/Hybrid_based_Features/ChildSafetyChecker/main.py
Digital_India_Act/Hybrid_based_Features/ChildSafetyChecker/models.py
Digital_India_Act/Hybrid_based_Features/ChildSafetyChecker/rule_engine.py
Digital_India_Act/Hybrid_based_Features/ChildSafetyChecker/scraper.py
Digital_India_Act/LLM_based_Features/Consent_screen_check.py
Digital_India_Act/LLM_based_Features/Content_moderation_filter_check.py
Digital_India_Act/LLM_based_Features/Dark_patterns_check.py
Digital_India_Act/LLM_based_Features/Data_minimization_checker.py
Digital_India_Act/LLM_based_Features/__init__.py
Digital_India_Act/LLM_based_Features/dummy.py
Digital_India_Act/LLM_based_Features/grievance_extractor.py
Digital_India_Act/LLM_based_Features/grivance_redressal_checker.py
Digital_India_Act/LLM_based_Features/test_scaper.py
Digital_India_Act/LLM_based_Features/fairness_detect/__init__.py
Digital_India_Act/LLM_based_Features/fairness_detect/advance.py
Digital_India_Act/LLM_based_Features/fairness_detect/bias_audit_direct.py
dia_compliance_tool-0.2.1.dist-info/METADATA
dia_compliance_tool-0.2.1.dist-info/WHEEL
dia_compliance_tool-0.2.1.dist-info/top_level.txt
dia_compliance_tool-0.2.1.dist-info/RECORD
