Metadata-Version: 2.4
Name: dia-compliance-tool
Version: 0.2.1
Summary: Digital India Act compliance checker with rule-based and LLM-based analysis
Author: Your Name
Requires-Python: >=3.8
Requires-Dist: requests>=2.0
Requires-Dist: beautifulsoup4>=4.9
Requires-Dist: lxml>=4.9
Requires-Dist: pdfminer.six>=20221105
Requires-Dist: groq<1.0,>=0.4.2
Requires-Dist: pydantic>=2.9
Requires-Dist: python-dotenv>=1.0.0
Requires-Dist: trafilatura>=1.6.0
Requires-Dist: pandas>=1.5.0
Provides-Extra: api
Requires-Dist: fastapi==0.104.1; extra == "api"
Requires-Dist: uvicorn==0.24.0; extra == "api"
Requires-Dist: python-multipart==0.0.6; extra == "api"
Provides-Extra: browser
Requires-Dist: playwright>=1.40; extra == "browser"
Requires-Dist: axe-selenium-python; extra == "browser"
Provides-Extra: ml
Requires-Dist: tensorflow==2.15.0; extra == "ml"
Requires-Dist: tf-keras==2.15.0; extra == "ml"
Requires-Dist: deepface==0.0.79; extra == "ml"
Provides-Extra: all
Requires-Dist: fastapi==0.104.1; extra == "all"
Requires-Dist: uvicorn==0.24.0; extra == "all"
Requires-Dist: python-multipart==0.0.6; extra == "all"
Requires-Dist: playwright>=1.40; extra == "all"
Requires-Dist: axe-selenium-python; extra == "all"
Requires-Dist: tensorflow==2.15.0; extra == "all"
Requires-Dist: tf-keras==2.15.0; extra == "all"
Requires-Dist: deepface==0.0.79; extra == "all"
Dynamic: author
Dynamic: provides-extra
Dynamic: requires-dist
Dynamic: requires-python
Dynamic: summary
